LICENSE
MANIFEST.in
README.rst
setup.py
amunra_sphinx_theme/__init__.py
amunra_sphinx_theme/layout.html
amunra_sphinx_theme/theme.conf
amunra_sphinx_theme/version.py
amunra_sphinx_theme.egg-info/PKG-INFO
amunra_sphinx_theme.egg-info/SOURCES.txt
amunra_sphinx_theme.egg-info/dependency_links.txt
amunra_sphinx_theme.egg-info/entry_points.txt
amunra_sphinx_theme.egg-info/top_level.txt
amunra_sphinx_theme/static/css/amunra.css
docs/.nojekyll
docs/Makefile
docs/conf.py
docs/index.rst
docs/make.bat
docs/quickstart.rst
docs/_static/images/amunra-preview.png