Metadata-Version: 1.1
Name: amunra-sphinx-theme
Version: 0.2
Summary: A beautiful, minimalist, and responsive theme for your Sphinx projects.
Home-page: https://barentsen.github.io/amunra-sphinx-theme/
Author: Geert Barentsen
Author-email: hello@geert.io
License: BSD
Platform: UNKNOWN
Classifier: Development Status :: 5 - Production/Stable
Classifier: Intended Audience :: Developers
Classifier: License :: OSI Approved :: BSD License
Classifier: Operating System :: OS Independent
Classifier: Programming Language :: Python
Classifier: Topic :: Documentation
Classifier: Topic :: Software Development :: Documentation
